LICENSE.txt
MANIFEST.in
README.rst
requirements.txt
setup.cfg
setup.py
botocore/__init__.py
botocore/args.py
botocore/auth.py
botocore/awsrequest.py
botocore/client.py
botocore/compat.py
botocore/config.py
botocore/configloader.py
botocore/credentials.py
botocore/endpoint.py
botocore/errorfactory.py
botocore/exceptions.py
botocore/handlers.py
botocore/hooks.py
botocore/loaders.py
botocore/model.py
botocore/paginate.py
botocore/parsers.py
botocore/regions.py
botocore/response.py
botocore/retryhandler.py
botocore/serialize.py
botocore/session.py
botocore/signers.py
botocore/stub.py
botocore/translate.py
botocore/utils.py
botocore/validate.py
botocore/waiter.py
botocore/data/_retry.json
botocore/data/endpoints.json
botocore/data/acm/2015-12-08/examples-1.json
botocore/data/acm/2015-12-08/paginators-1.json
botocore/data/acm/2015-12-08/service-2.json
botocore/data/apigateway/2015-07-09/examples-1.json
botocore/data/apigateway/2015-07-09/paginators-1.json
botocore/data/apigateway/2015-07-09/service-2.json
botocore/data/application-autoscaling/2016-02-06/examples-1.json
botocore/data/application-autoscaling/2016-02-06/paginators-1.json
botocore/data/application-autoscaling/2016-02-06/service-2.json
botocore/data/appstream/2016-12-01/examples-1.json
botocore/data/appstream/2016-12-01/service-2.json
botocore/data/autoscaling/2011-01-01/examples-1.json
botocore/data/autoscaling/2011-01-01/paginators-1.json
botocore/data/autoscaling/2011-01-01/service-2.json
botocore/data/batch/2016-08-10/examples-1.json
botocore/data/batch/2016-08-10/paginators-1.json
botocore/data/batch/2016-08-10/service-2.json
botocore/data/budgets/2016-10-20/examples-1.json
botocore/data/budgets/2016-10-20/paginators-1.json
botocore/data/budgets/2016-10-20/service-2.json
botocore/data/clouddirectory/2016-05-10/paginators-1.json
botocore/data/clouddirectory/2016-05-10/service-2.json
botocore/data/cloudformation/2010-05-15/examples-1.json
botocore/data/cloudformation/2010-05-15/paginators-1.json
botocore_meiqia.egg-info/PKG-INFO
botocore_meiqia.egg-info/SOURCES.txt
botocore_meiqia.egg-info/dependency_links.txt
botocore_meiqia.egg-info/requires.txt
botocore_meiqia.egg-info/top_level.txt
